microcosmClient/__init__.py
microcosmClient/microcosm.py
microcosm_client-0.1.0.dist-info/METADATA
microcosm_client-0.1.0.dist-info/WHEEL
microcosm_client-0.1.0.dist-info/top_level.txt
microcosm_client-0.1.0.dist-info/RECORD
