Metadata-Version: 2.4
Name: microcosm-client
Version: 0.1.0
Summary: Async Microcosm API client wrapper
Author: kamo.moe
License: MIT
Requires-Python: >=3.11
Requires-Dist: httpx
Requires-Dist: atproto
